pixcompress/__init__.py
pixcompress/cli.py
pixcompress/core.py
pixcompress-0.1.3.dist-info/licenses/LICENSE
pixcompress-0.1.3.dist-info/METADATA
pixcompress-0.1.3.dist-info/WHEEL
pixcompress-0.1.3.dist-info/entry_points.txt
pixcompress-0.1.3.dist-info/top_level.txt
pixcompress-0.1.3.dist-info/RECORD
